mathaid/__init__.py
mathaid/factorial.py
mathaid/lcm_hcf.py
mathaid/num_conversion.py
mathaid/prime.py
mathutils/__init__.py
mathutils/factorial.py
mathutils/lcm_hcf.py
mathutils/num_conversion.py
mathutils/prime.py
tests/__init__.py
tests/test_factorial.py
tests/test_lcm_hcf.py
tests/test_num_conversion.py
tests/test_prime.py
mathaid-1.0.0.dist-info/METADATA
mathaid-1.0.0.dist-info/WHEEL
mathaid-1.0.0.dist-info/top_level.txt
mathaid-1.0.0.dist-info/RECORD
