Metadata-Version: 2.1
Name: mathaid
Version: 1.0.0
Summary: A package for mathematical utility functions
Home-page: https://github.com/spikyshade/mathaid
Author: SpikyShade
Author-email: codeswithdevesh@gmail.com
Classifier: Development Status :: 5 - Production/Stable
Classifier: Intended Audience :: Developers
Classifier: License :: OSI Approved :: MIT License
Classifier: Programming Language :: Python :: 3
Classifier: Programming Language :: Python :: 3.6
Classifier: Programming Language :: Python :: 3.7
Classifier: Programming Language :: Python :: 3.8
Classifier: Programming Language :: Python :: 3.9
Classifier: Programming Language :: Python :: 3.10
Requires-Python: >=3.6
